cbcov-0.2.data/scripts/cbcov
covid_predict/__init__.py
covid_predict/io/Csse_data.py
covid_predict/io/DataGouvFr.py
covid_predict/io/OpenCovid19.py
covid_predict/io/__init__.py
covid_predict/models/__init__.py
covid_predict/models/visu.py
covid_predict/models/zm.py
covid_predict/util/__init__.py
covid_predict/util/math_util.py
covid_predict/util/plot_util.py
cbcov-0.2.dist-info/METADATA
cbcov-0.2.dist-info/WHEEL
cbcov-0.2.dist-info/top_level.txt
cbcov-0.2.dist-info/RECORD
