Metadata-Version: 2.1
Name: cbcov
Version: 0.2
Summary: Simple models for covid prediction
Home-page: https://plmlab.math.cnrs.fr/atrouve/cb-epid-covid.git
Author: CB
Author-email: alain.trouve@gmail.com
License: UNKNOWN
Platform: UNKNOWN
Classifier: Programming Language :: Python :: 3
Classifier: License :: OSI Approved :: MIT License
Classifier: Operating System :: OS Independent
